{
  "$schema": "https://developer.microsoft.com/json-schemas/fabric/item/report/definition/visualContainer/2.1.0/schema.json",
  "name": "f7e54aff07a836e975cc",
  "position": {
    "x": 782.5,
    "y": 557.5,
    "z": 10000,
    "height": 72.5,
    "width": 260,
    "tabOrder": 11000
  },
  "visual": {
    "visualType": "card",
    "query": {
      "queryState": {
        "Values": {
          "projections": [
            {
              "field": {
                "Aggregation": {
                  "Expression": {
                    "Column": {
                      "Expression": {
                        "SourceRef": {
                          "Entity": "Product Subcategories Lookup"
                        }
                      },
                      "Property": "SubcategoryName"
                    }
                  },
                  "Function": 3
                }
              },
              "queryRef": "Min(Product Subcategories Lookup.SubcategoryName)",
              "nativeQueryRef": "First SubcategoryName"
            }
          ]
        }
      }
    },
    "objects": {
      "labels": [
        {
          "properties": {
            "color": {
              "solid": {
                "color": {
                  "expr": {
                    "ThemeDataColor": {
                      "ColorId": 2,
                      "Percent": 0
                    }
                  }
                }
              }
            },
            "fontSize": {
              "expr": {
                "Literal": {
                  "Value": "29D"
                }
              }
            }
          }
        }
      ],
      "categoryLabels": [
        {
          "properties": {
            "color": {
              "solid": {
                "color": {
                  "expr": {
                    "Literal": {
                      "Value": "'#ffffff'"
                    }
                  }
                }
              }
            }
          }
        }
      ]
    },
    "visualContainerObjects": {
      "background": [
        {
          "properties": {
            "color": {
              "solid": {
                "color": {
                  "expr": {
                    "ThemeDataColor": {
                      "ColorId": 1,
                      "Percent": 0
                    }
                  }
                }
              }
            }
          }
        }
      ],
      "title": [
        {
          "properties": {
            "show": {
              "expr": {
                "Literal": {
                  "Value": "true"
                }
              }
            },
            "text": {
              "expr": {
                "Literal": {
                  "Value": "'most order product Type'"
                }
              }
            },
            "fontColor": {
              "solid": {
                "color": {
                  "expr": {
                    "Literal": {
                      "Value": "'#ffffff'"
                    }
                  }
                }
              }
            },
            "alignment": {
              "expr": {
                "Literal": {
                  "Value": "'center'"
                }
              }
            }
          }
        }
      ]
    },
    "drillFilterOtherVisuals": true
  },
  "filterConfig": {
    "filters": [
      {
        "name": "ab4b8820c375bdfa3582",
        "field": {
          "Column": {
            "Expression": {
              "SourceRef": {
                "Entity": "Product Subcategories Lookup"
              }
            },
            "Property": "SubcategoryName"
          }
        },
        "type": "TopN",
        "filter": {
          "Version": 2,
          "From": [
            {
              "Name": "subquery",
              "Expression": {
                "Subquery": {
                  "Query": {
                    "Version": 2,
                    "From": [
                      {
                        "Name": "p",
                        "Entity": "Product Subcategories Lookup",
                        "Type": 0
                      },
                      {
                        "Name": "m",
                        "Entity": "Measure Table (2)",
                        "Type": 0
                      }
                    ],
                    "Select": [
                      {
                        "Column": {
                          "Expression": {
                            "SourceRef": {
                              "Source": "p"
                            }
                          },
                          "Property": "SubcategoryName"
                        },
                        "Name": "field"
                      }
                    ],
                    "OrderBy": [
                      {
                        "Direction": 2,
                        "Expression": {
                          "Measure": {
                            "Expression": {
                              "SourceRef": {
                                "Source": "m"
                              }
                            },
                            "Property": "Total Orders"
                          }
                        }
                      }
                    ],
                    "Top": 1
                  }
                }
              },
              "Type": 2
            },
            {
              "Name": "p",
              "Entity": "Product Subcategories Lookup",
              "Type": 0
            }
          ],
          "Where": [
            {
              "Condition": {
                "In": {
                  "Expressions": [
                    {
                      "Column": {
                        "Expression": {
                          "SourceRef": {
                            "Source": "p"
                          }
                        },
                        "Property": "SubcategoryName"
                      }
                    }
                  ],
                  "Table": {
                    "SourceRef": {
                      "Source": "subquery"
                    }
                  }
                }
              }
            }
          ]
        },
        "howCreated": "User"
      }
    ]
  }
}